{"content":[{"id":"64262f4c","settings":{"content_width":"full","animation":"fadeIn","animation_duration":"fast","margin":{"unit":"px","top":"80","right":"0","bottom":"0","left":"0","isLinked":""},"margin_tablet":{"unit":"px","top":"0","right":"0","bottom":"0","left":"0","isLinked":""},"padding":{"unit":"px","top":"0","right":"40","bottom":"0","left":"40","isLinked":""},"padding_mobile":{"unit":"px","top":"0","right":"20","bottom":"0","left":"20","isLinked":""},"background_overlay_background":"classic","background_overlay_opacity":{"unit":"px","size":"0","sizes":[]},"__globals__":{"background_color":"globals\/colors?id=aba7187"}},"elements":[{"id":"665c0996","settings":{"heading_text":"CONTACT US","description_text":"Ready to build on a strong foundation? Get in touch with us and let us know about your next big project or any other queries. ","group_1_links_subheading":"Let's talk","group_1_repeater":[{"group_1_label":"+123 456 7890","_id":"4b4e77f"},{"group_1_icon":{"value":"fas fa-envelope","library":"fa-solid"},"group_1_label":"contact@mysite.com","group_1_platform":"email","_id":"8dcc25a"}],"group_1_text_subheading":"Hours","group_1_text_textarea":"M-F 9am-6pm","group_1_social_subheading":"Follow","group_1_social_repeater":[{"group_1_social_label":"Instagram","group_1_social_link":{"url":"https:\/\/www.instagram.com\/"},"_id":"44c2911"},{"group_1_social_label":"Tiktok","group_1_social_icon":{"value":"fab fa-tiktok","library":"fa-brands"},"group_1_social_link":{"url":"https:\/\/www.tiktok.com\/"},"_id":"da4a093"},{"group_1_social_label":"X (Twitter)","group_1_social_icon":{"value":"fab fa-x-twitter","library":"fa-brands"},"group_1_social_link":{"url":"https:\/\/www.twitter.com\/"},"_id":"249e055"}],"group_2_links_subheading":"Hours","group_2_repeater":[{"group_2_label":"Call","_id":"e9e9f49"},{"group_2_icon":{"value":"fas fa-envelope","library":"fa-solid"},"group_2_label":"Email","group_2_platform":"email","_id":"71edf78"}],"group_2_text_subheading":"Hours","group_2_text_textarea":"Mon - Fri   9am-6pm","group_2_social_subheading":"Follow","group_2_social_repeater":[{"group_2_social_label":"Instagram","group_2_social_link":{"url":"https:\/\/www.instagram.com\/"},"_id":"33f5226"},{"group_2_social_label":"Tiktok","group_2_social_icon":{"value":"fab fa-tiktok","library":"fa-brands"},"group_2_social_link":{"url":"https:\/\/www.tiktok.com\/"},"_id":"e47f955"},{"group_2_social_label":"X (Twitter)","group_2_social_icon":{"value":"fab fa-x-twitter","library":"fa-brands"},"group_2_social_link":{"url":"https:\/\/www.twitter.com\/"},"_id":"dfe9509"}],"group_3_switcher":"","group_3_links_subheading":"Visit","group_3_repeater":[{"group_3_icon":{"value":"fas fa-map-marker-alt","library":"fa-solid"},"group_3_label":"Visit","_id":"91c8ec0"}],"group_3_text_subheading":"Hours","group_3_text_textarea":"M-F 9am-6pm","group_3_social_subheading":"Follow","group_3_social_repeater":[{"group_3_social_label":"Instagram","group_3_social_link":{"url":"https:\/\/www.instagram.com\/"},"_id":"8048190"},{"group_3_social_label":"Tiktok","group_3_social_icon":{"value":"fab fa-tiktok","library":"fa-brands"},"group_3_social_link":{"url":"https:\/\/www.tiktok.com\/"},"_id":"f0f3af3"},{"group_3_social_label":"X (Twitter)","group_3_social_icon":{"value":"fab fa-x-twitter","library":"fa-brands"},"group_3_social_link":{"url":"https:\/\/www.twitter.com\/"},"_id":"ef76585"}],"group_4_links_subheading":"Follow","group_4_repeater":[{"group_4_label":"Call","_id":"23c8b6a"},{"group_4_icon":{"value":"fas fa-envelope","library":"fa-solid"},"group_4_label":"Email","group_4_platform":"email","_id":"80f8cf6"}],"group_4_text_subheading":"Hours","group_4_text_textarea":"M-F 9am-6pm","group_4_social_subheading":"Follow Us","group_4_social_repeater":[{"group_4_social_label":"Instagram","group_4_social_link":{"url":"https:\/\/www.instagram.com\/"},"_id":"0fa5b16"},{"group_4_social_label":"Tiktok","group_4_social_icon":{"value":"fab fa-tiktok","library":"fa-brands"},"group_4_social_link":{"url":"https:\/\/www.tiktok.com\/"},"_id":"c189621"},{"group_4_social_label":"X (Twitter)","group_4_social_icon":{"value":"fab fa-x-twitter","library":"fa-brands"},"group_4_social_link":{"url":"https:\/\/www.twitter.com\/"},"_id":"7b3a1ea"}],"map_address":"London Eye, London, United Kingdom","contact_details_columns_locate":"3","space_between_widgets":{"column":"40","row":"0","isLinked":"","unit":"px"},"text_spacing":{"unit":"px","size":"24","sizes":[]},"map_zoom":{"unit":"px","size":"14","sizes":[]},"map_stretch":"","map_height_mobile":{"unit":"px","size":"272","sizes":[]},"show_map_border":"yes","map_shape":"custom","map_shape_custom":{"unit":"px","top":"32","right":"32","bottom":"32","left":"32","isLinked":"1"},"background_background":"classic","box_element_spacing":{"unit":"px","size":"60","sizes":[]},"box_gap":{"unit":"px","size":"100","sizes":[]},"box_shape":"custom","box_shape_custom":{"unit":"px","top":"40","right":"40","bottom":"40","left":"40","isLinked":"1"},"__globals__":{"heading_color":"globals\/colors?id=text","contact_details_subheading_color":"globals\/colors?id=accent","contact_details_icon_color":"globals\/colors?id=text","contact_details_social_icon_color":"globals\/colors?id=text","contact_details_social_icon_hover_color":"globals\/colors?id=accent","contact_details_icon_hover_color":"globals\/colors?id=accent","contact_details_text_typography_typography":"globals\/typography?id=text","contact_details_subheading_typography_typography":"globals\/typography?id=text","map_border_color":"globals\/colors?id=accent","background_color":"globals\/colors?id=aba7187"},"contact_details_text_spacing":{"unit":"px","size":"16","sizes":[]},"contact_details_spacing":{"unit":"px","size":"0","sizes":[]},"contact_details_social_icon_gap":{"unit":"px","size":"20","sizes":[]},"box_padding":{"unit":"px","top":"0","right":"0","bottom":"0","left":"0","isLinked":"1"},"box_padding_tablet":{"unit":"px","top":"","right":"","bottom":"","left":"","isLinked":"1"},"box_padding_mobile":{"unit":"px","top":"","right":"","bottom":"","left":"","isLinked":"1"},"_background_background":"classic"},"elements":[],"isInner":false,"widgetType":"contact","elType":"widget"}],"isInner":"","elType":"container"}],"settings":{"template":"elementor_header_footer","__globals__":{"background_color":"globals\/colors?id=secondary"}},"metadata":[]}